fourdle/__init__.py
fourdle/data/filter.py
fourdle/data/words.txt
fourdle/data/words_alpha.txt
fourdle/data/words_length_4.txt
fourdle/data/words_length_4_alpha_base.txt
fourdle/fourdle.egg-info/PKG-INFO
fourdle/fourdle.egg-info/SOURCES.txt
fourdle/fourdle.egg-info/dependency_links.txt
fourdle/fourdle.egg-info/top_level.txt
fourdle/fourdle.py
fourdle/my_package.egg-info/PKG-INFO
fourdle/my_package.egg-info/SOURCES.txt
fourdle/my_package.egg-info/dependency_links.txt
fourdle/my_package.egg-info/top_level.txt
fourdle-0.1.8.dist-info/LICENSE
fourdle-0.1.8.dist-info/METADATA
fourdle-0.1.8.dist-info/WHEEL
fourdle-0.1.8.dist-info/RECORD
