Metadata-Version: 2.1
Name: fourdle
Version: 0.1.8
Summary: Small fourdle game
Author: Filip Cederquist
Requires-Python: >=3.9,<4.0
Classifier: Programming Language :: Python :: 3
Classifier: Programming Language :: Python :: 3.9
Classifier: Programming Language :: Python :: 3.10
Classifier: Programming Language :: Python :: 3.11
